[{"id":"130982001","level":5,"name":"新华路街道"},{"id":"130982002","level":5,"name":"西环路街道"},{"id":"130982003","level":5,"name":"永丰路街道"},{"id":"130982004","level":5,"name":"中华路办事处"},{"id":"130982100","level":5,"name":"出岸镇"},{"id":"130982101","level":5,"name":"石门桥镇"},{"id":"130982102","level":5,"name":"吕公堡镇"},{"id":"130982103","level":5,"name":"长丰镇"},{"id":"130982104","level":5,"name":"鄚州镇"},{"id":"130982105","level":5,"name":"苟各庄镇"},{"id":"130982106","level":5,"name":"梁召镇"},{"id":"130982107","level":5,"name":"辛中驿镇"},{"id":"130982108","level":5,"name":"麻家坞镇"},{"id":"130982203","level":5,"name":"议论堡乡"},{"id":"130982204","level":5,"name":"青塔乡"},{"id":"130982205","level":5,"name":"北辛庄乡"},{"id":"130982206","level":5,"name":"七间房乡"},{"id":"130982207","level":5,"name":"北汉乡"},{"id":"130982208","level":5,"name":"于村乡"},{"id":"130982400","level":5,"name":"华北石油管理局"},{"id":"130982500","level":5,"name":"开发区管理委员会"},{"id":"130982501","level":5,"name":"河北任丘雁翎工业园区"}]