[{"id":"150784001","level":5,"name":"拉布达林街道"},{"id":"150784002","level":5,"name":"上库力街道"},{"id":"150784101","level":5,"name":"黑山头镇"},{"id":"150784103","level":5,"name":"莫尔道嘎镇"},{"id":"150784104","level":5,"name":"恩和哈达镇"},{"id":"150784200","level":5,"name":"三河回族乡"},{"id":"150784210","level":5,"name":"恩和俄罗斯族民族乡"},{"id":"150784211","level":5,"name":"蒙兀室韦苏木"},{"id":"150784212","level":5,"name":"奇乾乡"},{"id":"150784400","level":5,"name":"海拉尔农垦集团有限公司拉布大林农场分公司"},{"id":"150784401","level":5,"name":"三河金騋农牧有限责任公司"},{"id":"150784402","level":5,"name":"海拉尔农垦集团有限责任公司上库力农场分公"},{"id":"150784403","level":5,"name":"海拉尔农垦集团有限责任公司苏沁牧场分公司"}]