[{"id":"210114001","level":5,"name":"迎宾路街道"},{"id":"210114003","level":5,"name":"陵西街道"},{"id":"210114005","level":5,"name":"于洪街道"},{"id":"210114007","level":5,"name":"北陵街道"},{"id":"210114009","level":5,"name":"沙岭街道"},{"id":"210114010","level":5,"name":"南阳湖街道"},{"id":"210114011","level":5,"name":"城东湖街道"},{"id":"210114012","level":5,"name":"平罗街道"},{"id":"210114013","level":5,"name":"马三家街道"},{"id":"210114014","level":5,"name":"造化街道"},{"id":"210114015","level":5,"name":"大兴街道"},{"id":"210114016","level":5,"name":"光辉街道"},{"id":"210114401","level":5,"name":"马三家劳动教养院"},{"id":"210114402","level":5,"name":"光辉农场"},{"id":"210114404","level":5,"name":"监狱城"}]