[{"id":"231226100","level":5,"name":"绥棱镇"},{"id":"231226101","level":5,"name":"上集镇"},{"id":"231226102","level":5,"name":"四海店镇"},{"id":"231226103","level":5,"name":"双岔河镇"},{"id":"231226200","level":5,"name":"靠山乡"},{"id":"231226201","level":5,"name":"后头乡"},{"id":"231226203","level":5,"name":"长山乡"},{"id":"231226205","level":5,"name":"克音河乡"},{"id":"231226206","level":5,"name":"绥中乡"},{"id":"231226207","level":5,"name":"泥尔河乡"},{"id":"231226210","level":5,"name":"阁山乡"},{"id":"231226400","level":5,"name":"阁山林场"},{"id":"231226401","level":5,"name":"四海店林场"},{"id":"231226402","level":5,"name":"三吉台林场"},{"id":"231226403","level":5,"name":"半截河林场"},{"id":"231226404","level":5,"name":"绥棱林业局"},{"id":"231226500","level":5,"name":"绥棱农场"},{"id":"231226580","level":5,"name":"种马场"},{"id":"231226581","level":5,"name":"良种场"},{"id":"231226582","level":5,"name":"奶山羊场"}]