[{"id":"320211001","level":5,"name":"河埒街道"},{"id":"320211002","level":5,"name":"荣巷街道"},{"id":"320211003","level":5,"name":"蠡园街道"},{"id":"320211004","level":5,"name":"蠡湖街道"},{"id":"320211006","level":5,"name":"华庄街道"},{"id":"320211007","level":5,"name":"太湖街道"},{"id":"320211008","level":5,"name":"雪浪街道"},{"id":"320211009","level":5,"name":"马山街道"},{"id":"320211050","level":5,"name":"旺庄街道"},{"id":"320211051","level":5,"name":"硕放街道"},{"id":"320211052","level":5,"name":"江溪街道"},{"id":"320211053","level":5,"name":"新安街道"},{"id":"320211054","level":5,"name":"梅村街道"},{"id":"320211055","level":5,"name":"鸿山街道"},{"id":"320211101","level":5,"name":"胡埭镇"},{"id":"320211450","level":5,"name":"无锡新加坡工业园"},{"id":"320211451","level":5,"name":"无锡高新技术产业开发区"},{"id":"320211452","level":5,"name":"无锡高新区综合保税区"},{"id":"320211453","level":5,"name":"无锡太湖国际科技园"}]