[{"id":"330502001","level":5,"name":"月河街道"},{"id":"330502002","level":5,"name":"朝阳街道"},{"id":"330502003","level":5,"name":"爱山街道"},{"id":"330502004","level":5,"name":"飞英街道"},{"id":"330502005","level":5,"name":"龙泉街道"},{"id":"330502006","level":5,"name":"凤凰街道"},{"id":"330502007","level":5,"name":"康山街道"},{"id":"330502008","level":5,"name":"仁皇山街道"},{"id":"330502009","level":5,"name":"滨湖街道"},{"id":"330502010","level":5,"name":"龙溪街道"},{"id":"330502011","level":5,"name":"杨家埠街道"},{"id":"330502012","level":5,"name":"环渚街道"},{"id":"330502013","level":5,"name":"湖东街道"},{"id":"330502100","level":5,"name":"织里镇"},{"id":"330502101","level":5,"name":"八里店镇"},{"id":"330502102","level":5,"name":"妙西镇"},{"id":"330502104","level":5,"name":"埭溪镇"},{"id":"330502105","level":5,"name":"东林镇"},{"id":"330502200","level":5,"name":"道场乡"}]