[{"id":"340621100","level":5,"name":"濉溪镇"},{"id":"340621101","level":5,"name":"韩村镇"},{"id":"340621102","level":5,"name":"刘桥镇"},{"id":"340621103","level":5,"name":"五沟镇"},{"id":"340621104","level":5,"name":"临涣镇"},{"id":"340621105","level":5,"name":"双堆集镇"},{"id":"340621106","level":5,"name":"铁佛镇"},{"id":"340621107","level":5,"name":"南坪镇"},{"id":"340621108","level":5,"name":"百善镇"},{"id":"340621109","level":5,"name":"孙町镇"},{"id":"340621110","level":5,"name":"四铺镇"},{"id":"340621400","level":5,"name":"濉溪县经济开发区"},{"id":"340621401","level":5,"name":"濉溪县濉芜产业园"}]