[{"id":"350423100","level":5,"name":"龙津镇"},{"id":"350423101","level":5,"name":"嵩溪镇"},{"id":"350423102","level":5,"name":"嵩口镇"},{"id":"350423103","level":5,"name":"灵地镇"},{"id":"350423104","level":5,"name":"长校镇"},{"id":"350423201","level":5,"name":"温郊乡"},{"id":"350423202","level":5,"name":"林畲乡"},{"id":"350423203","level":5,"name":"田源乡"},{"id":"350423204","level":5,"name":"沙芜乡"},{"id":"350423205","level":5,"name":"赖坊乡"},{"id":"350423206","level":5,"name":"余朋乡"},{"id":"350423208","level":5,"name":"李家乡"},{"id":"350423209","level":5,"name":"里田乡"}]