[{"id":"361024001","level":5,"name":"巴山镇"},{"id":"361024002","level":5,"name":"马安镇"},{"id":"361024003","level":5,"name":"三山乡"},{"id":"361024004","level":5,"name":"白陂乡"},{"id":"361024006","level":5,"name":"河上镇"},{"id":"361024008","level":5,"name":"孙坊镇"},{"id":"361024009","level":5,"name":"白路乡"},{"id":"361024012","level":5,"name":"石庄乡"},{"id":"361024013","level":5,"name":"航埠镇"},{"id":"361024014","level":5,"name":"六家桥乡"},{"id":"361024015","level":5,"name":"郭圩乡"},{"id":"361024016","level":5,"name":"礼陂镇"},{"id":"361024017","level":5,"name":"许坊乡"},{"id":"361024018","level":5,"name":"桃源乡"},{"id":"361024019","level":5,"name":"相山镇"}]