[{"id":"370283001","level":5,"name":"东阁街道"},{"id":"370283002","level":5,"name":"李园街道"},{"id":"370283003","level":5,"name":"同和街道"},{"id":"370283004","level":5,"name":"凤台街道"},{"id":"370283005","level":5,"name":"白沙河街道"},{"id":"370283101","level":5,"name":"古岘镇"},{"id":"370283102","level":5,"name":"仁兆镇"},{"id":"370283105","level":5,"name":"南村镇"},{"id":"370283108","level":5,"name":"蓼兰镇"},{"id":"370283109","level":5,"name":"崔家集镇"},{"id":"370283110","level":5,"name":"明村镇"},{"id":"370283113","level":5,"name":"田庄镇"},{"id":"370283116","level":5,"name":"新河镇"},{"id":"370283119","level":5,"name":"店子镇"},{"id":"370283120","level":5,"name":"大泽山镇"},{"id":"370283122","level":5,"name":"旧店镇"},{"id":"370283124","level":5,"name":"云山镇"},{"id":"370283400","level":5,"name":"平度外向型工业加工区"}]