[{"id":"410811001","level":5,"name":"东方红街道"},{"id":"410811002","level":5,"name":"焦东街道"},{"id":"410811003","level":5,"name":"百间房街道"},{"id":"410811004","level":5,"name":"太行街道"},{"id":"410811005","level":5,"name":"艺新街道"},{"id":"410811006","level":5,"name":"光亚街道"},{"id":"410811007","level":5,"name":"定和街道"},{"id":"410811008","level":5,"name":"中星街道"},{"id":"410811009","level":5,"name":"新城街道"},{"id":"410811060","level":5,"name":"李万街道"},{"id":"410811061","level":5,"name":"文苑街道"},{"id":"410811062","level":5,"name":"文昌街道"},{"id":"410811100","level":5,"name":"阳庙镇"},{"id":"410811101","level":5,"name":"宁郭镇"},{"id":"410811203","level":5,"name":"苏家作乡"}]