[{"id":"411481100","level":5,"name":"演集镇"},{"id":"411481101","level":5,"name":"城关镇"},{"id":"411481102","level":5,"name":"芒山镇"},{"id":"411481103","level":5,"name":"高庄镇"},{"id":"411481104","level":5,"name":"酇城镇"},{"id":"411481105","level":5,"name":"裴桥镇"},{"id":"411481106","level":5,"name":"马桥镇"},{"id":"411481107","level":5,"name":"薛湖镇"},{"id":"411481108","level":5,"name":"蒋口镇"},{"id":"411481109","level":5,"name":"陈集镇"},{"id":"411481110","level":5,"name":"十八里镇"},{"id":"411481111","level":5,"name":"太邱镇"},{"id":"411481112","level":5,"name":"李寨镇"},{"id":"411481113","level":5,"name":"苗桥镇"},{"id":"411481114","level":5,"name":"顺和镇"},{"id":"411481115","level":5,"name":"茴村镇"},{"id":"411481116","level":5,"name":"酇阳镇"},{"id":"411481117","level":5,"name":"龙岗镇"},{"id":"411481118","level":5,"name":"马牧镇"},{"id":"411481119","level":5,"name":"王集镇"},{"id":"411481120","level":5,"name":"刘河镇"},{"id":"411481200","level":5,"name":"城厢乡"},{"id":"411481201","level":5,"name":"候岭乡"},{"id":"411481202","level":5,"name":"黄口乡"},{"id":"411481203","level":5,"name":"新桥乡"},{"id":"411481204","level":5,"name":"双桥乡"},{"id":"411481207","level":5,"name":"卧龙乡"},{"id":"411481217","level":5,"name":"条河乡"},{"id":"411481219","level":5,"name":"陈官庄乡"}]