[{"id":"421087100","level":5,"name":"新江口镇"},{"id":"421087101","level":5,"name":"南海镇"},{"id":"421087102","level":5,"name":"八宝镇"},{"id":"421087103","level":5,"name":"宛市镇"},{"id":"421087104","level":5,"name":"老城镇"},{"id":"421087105","level":5,"name":"陈店镇"},{"id":"421087106","level":5,"name":"王家桥镇"},{"id":"421087107","level":5,"name":"斯家场镇"},{"id":"421087108","level":5,"name":"杨林市镇"},{"id":"421087109","level":5,"name":"纸厂河镇"},{"id":"421087110","level":5,"name":"街河市镇"},{"id":"421087111","level":5,"name":"危水镇"},{"id":"421087112","level":5,"name":"刘家场镇"},{"id":"421087113","level":5,"name":"沙道观镇"},{"id":"421087200","level":5,"name":"万家乡"},{"id":"421087201","level":5,"name":"卸甲坪土家族乡"}]