[{"id":"421281001","level":5,"name":"蒲圻街道"},{"id":"421281002","level":5,"name":"赤马港街道"},{"id":"421281003","level":5,"name":"陆水湖街道"},{"id":"421281100","level":5,"name":"新店镇"},{"id":"421281101","level":5,"name":"赵李桥镇"},{"id":"421281102","level":5,"name":"茶庵岭镇"},{"id":"421281103","level":5,"name":"车埠镇"},{"id":"421281104","level":5,"name":"赤壁镇"},{"id":"421281105","level":5,"name":"柳山湖镇"},{"id":"421281106","level":5,"name":"神山镇"},{"id":"421281107","level":5,"name":"中伙铺镇"},{"id":"421281108","level":5,"name":"官塘驿镇"},{"id":"421281109","level":5,"name":"黄盖湖镇"},{"id":"421281200","level":5,"name":"余家桥乡"},{"id":"421281400","level":5,"name":"蒲纺工业园"},{"id":"421281401","level":5,"name":"官塘驿林场"},{"id":"421281402","level":5,"name":"羊楼洞茶场"},{"id":"421281403","level":5,"name":"沧湖开发区"},{"id":"421281404","level":5,"name":"赤壁市经济开发区"}]