[{"id":"430726100","level":5,"name":"楚江镇"},{"id":"430726101","level":5,"name":"蒙泉镇"},{"id":"430726102","level":5,"name":"夹山镇"},{"id":"430726103","level":5,"name":"易家渡镇"},{"id":"430726104","level":5,"name":"新关镇"},{"id":"430726105","level":5,"name":"皂市镇"},{"id":"430726106","level":5,"name":"维新镇"},{"id":"430726107","level":5,"name":"太平镇"},{"id":"430726108","level":5,"name":"磨市镇"},{"id":"430726109","level":5,"name":"壶瓶山镇"},{"id":"430726110","level":5,"name":"南北镇"},{"id":"430726200","level":5,"name":"二都乡"},{"id":"430726201","level":5,"name":"新铺乡"},{"id":"430726202","level":5,"name":"白云乡"},{"id":"430726203","level":5,"name":"三圣乡"},{"id":"430726204","level":5,"name":"子良乡"},{"id":"430726205","level":5,"name":"所街乡"},{"id":"430726206","level":5,"name":"雁池乡"},{"id":"430726207","level":5,"name":"罗坪乡"},{"id":"430726500","level":5,"name":"秀坪园艺场"},{"id":"430726502","level":5,"name":"东山峰农场"},{"id":"430726503","level":5,"name":"大同山林场"},{"id":"430726504","level":5,"name":"白云山林场"},{"id":"430726505","level":5,"name":"洛浦寺林场"},{"id":"430726506","level":5,"name":"夹山管理处"}]