[{"id":"441324001","level":5,"name":"龙城街道"},{"id":"441324100","level":5,"name":"麻榨镇"},{"id":"441324101","level":5,"name":"永汉镇"},{"id":"441324106","level":5,"name":"平陵镇"},{"id":"441324115","level":5,"name":"龙田镇"},{"id":"441324116","level":5,"name":"龙潭镇"},{"id":"441324117","level":5,"name":"地派镇"},{"id":"441324118","level":5,"name":"龙华镇"},{"id":"441324119","level":5,"name":"龙江镇"},{"id":"441324200","level":5,"name":"蓝田瑶族乡"},{"id":"441324453","level":5,"name":"龙门县密溪林场"},{"id":"441324570","level":5,"name":"南昆山生态旅游区管理委员会"}]