[{"id":"511802001","level":5,"name":"东城街道"},{"id":"511802002","level":5,"name":"西城街道"},{"id":"511802003","level":5,"name":"河北街道"},{"id":"511802004","level":5,"name":"青江街道"},{"id":"511802100","level":5,"name":"北郊镇"},{"id":"511802101","level":5,"name":"草坝镇"},{"id":"511802102","level":5,"name":"合江镇"},{"id":"511802103","level":5,"name":"大兴镇"},{"id":"511802104","level":5,"name":"对岩镇"},{"id":"511802105","level":5,"name":"沙坪镇"},{"id":"511802106","level":5,"name":"中里镇"},{"id":"511802107","level":5,"name":"上里镇"},{"id":"511802108","level":5,"name":"严桥镇"},{"id":"511802109","level":5,"name":"晏场镇"},{"id":"511802110","level":5,"name":"多营镇"},{"id":"511802111","level":5,"name":"碧峰峡镇"},{"id":"511802200","level":5,"name":"南郊乡"},{"id":"511802201","level":5,"name":"八步乡"},{"id":"511802202","level":5,"name":"观化乡"},{"id":"511802203","level":5,"name":"孔坪乡"},{"id":"511802204","level":5,"name":"凤鸣乡"},{"id":"511802205","level":5,"name":"望鱼乡"}]