[{"id":"513301100","level":5,"name":"炉城镇"},{"id":"513301101","level":5,"name":"姑咱镇"},{"id":"513301102","level":5,"name":"新都桥镇"},{"id":"513301201","level":5,"name":"雅拉乡"},{"id":"513301202","level":5,"name":"时济乡"},{"id":"513301203","level":5,"name":"前溪乡"},{"id":"513301204","level":5,"name":"舍联乡"},{"id":"513301205","level":5,"name":"麦崩乡"},{"id":"513301206","level":5,"name":"三合乡"},{"id":"513301207","level":5,"name":"金汤镇"},{"id":"513301208","level":5,"name":"捧塔乡"},{"id":"513301209","level":5,"name":"沙德镇"},{"id":"513301210","level":5,"name":"贡嘎山乡"},{"id":"513301211","level":5,"name":"普沙绒乡"},{"id":"513301212","level":5,"name":"吉居乡"},{"id":"513301213","level":5,"name":"瓦泽乡"},{"id":"513301214","level":5,"name":"呷巴乡"},{"id":"513301215","level":5,"name":"甲根坝乡"},{"id":"513301216","level":5,"name":"朋布西乡"},{"id":"513301217","level":5,"name":"塔公镇"},{"id":"513301218","level":5,"name":"孔玉乡"}]