[{"id":"710801","level":4,"name":"永和區"},{"id":"710802","level":4,"name":"新店區"},{"id":"710803","level":4,"name":"土城區"},{"id":"710804","level":4,"name":"蘆洲區"},{"id":"710805","level":4,"name":"五股區"},{"id":"710806","level":4,"name":"坪林區"},{"id":"710807","level":4,"name":"平溪區"},{"id":"710808","level":4,"name":"烏來區"},{"id":"710809","level":4,"name":"淡水區"},{"id":"710810","level":4,"name":"瑞芳區"},{"id":"710811","level":4,"name":"林口區"},{"id":"710812","level":4,"name":"三芝區"},{"id":"710813","level":4,"name":"八里區"},{"id":"710814","level":4,"name":"三峽區"},{"id":"710815","level":4,"name":"鶯歌區"},{"id":"710816","level":4,"name":"中和區"},{"id":"710817","level":4,"name":"樹林區"},{"id":"710818","level":4,"name":"深坑區"},{"id":"710819","level":4,"name":"板橋區"},{"id":"710820","level":4,"name":"石碇區"},{"id":"710821","level":4,"name":"新莊區"},{"id":"710822","level":4,"name":"泰山區"},{"id":"710823","level":4,"name":"三重區"},{"id":"710824","level":4,"name":"雙溪區"},{"id":"710825","level":4,"name":"貢寮區"},{"id":"710826","level":4,"name":"汐止區"},{"id":"710827","level":4,"name":"萬里區"},{"id":"710828","level":4,"name":"金山區"},{"id":"710829","level":4,"name":"石門區"}]