[{"id":"620100","level":3,"name":"兰州市"},{"id":"620200","level":3,"name":"嘉峪关市"},{"id":"620300","level":3,"name":"金昌市"},{"id":"620400","level":3,"name":"白银市"},{"id":"620500","level":3,"name":"天水市"},{"id":"620600","level":3,"name":"武威市"},{"id":"620700","level":3,"name":"张掖市"},{"id":"620800","level":3,"name":"平凉市"},{"id":"620900","level":3,"name":"酒泉市"},{"id":"621000","level":3,"name":"庆阳市"},{"id":"621100","level":3,"name":"定西市"},{"id":"621200","level":3,"name":"陇南市"},{"id":"622900","level":3,"name":"临夏回族自治州"},{"id":"623000","level":3,"name":"甘南藏族自治州"}]